iscc_sct/__init__.py
iscc_sct/cli.py
iscc_sct/code_semantic_text.py
iscc_sct/demo.py
iscc_sct/dev.py
iscc_sct/main.py
iscc_sct/models.py
iscc_sct/options.py
iscc_sct/samples.yml
iscc_sct/tokenizer.json
iscc_sct/utils.py
iscc_sct-0.1.4.dist-info/entry_points.txt
iscc_sct-0.1.4.dist-info/LICENSE
iscc_sct-0.1.4.dist-info/METADATA
iscc_sct-0.1.4.dist-info/WHEEL
iscc_sct-0.1.4.dist-info/RECORD
