Metadata-Version: 2.3
Name: iscc-sct
Version: 0.1.4
Summary: ISCC - Semantic Code Text
License: Apache-2.0
Keywords: iscc,text similarity,cross lingual,semantic similarity
Author: Titusz
Author-email: tp@piscc.io
Requires-Python: >=3.10,<3.14
Classifier: Development Status :: 4 - Beta
Classifier: Intended Audience :: Developers
Classifier: Intended Audience :: Science/Research
Classifier: License :: OSI Approved :: Apache Software License
Classifier: Natural Language :: English
Classifier: Operating System :: OS Independent
Classifier: Programming Language :: Python :: 3
Classifier: Programming Language :: Python :: 3.10
Classifier: Programming Language :: Python :: 3.11
Classifier: Programming Language :: Python :: 3.12
Classifier: Programming Language :: Python :: 3.13
Classifier: Topic :: Multimedia :: Graphics
Classifier: Topic :: Scientific/Engineering :: Artificial Intelligence
Classifier: Topic :: Scientific/Engineering :: Image Recognition
Classifier: Topic :: Scientific/Engineering :: Information Analysis
Classifier: Topic :: Software Development :: Libraries
Classifier: Topic :: Software Development :: Libraries :: Python Modules
Classifier: Topic :: System :: Archiving
Classifier: Topic :: System :: Clustering
Classifier: Topic :: System :: Distributed Computing
Classifier: Topic :: Text Processing
Classifier: Topic :: Text Processing :: General
Classifier: Topic :: Text Processing :: Indexing
Classifier: Topic :: Text Processing :: Linguistic
Provides-Extra: demo
Provides-Extra: gpu
Requires-Dist: blake3
Requires-Dist: certifi
Requires-Dist: charset-normalizer
Requires-Dist: gradio ; extra == "demo"
Requires-Dist: loguru
Requires-Dist: numpy
Requires-Dist: onnxruntime
Requires-Dist: onnxruntime-gpu ; extra == "gpu"
Requires-Dist: platformdirs
Requires-Dist: pybase64
Requires-Dist: pydantic
Requires-Dist: pydantic-settings
Requires-Dist: pyyaml
Requires-Dist: semantic-text-splitter
Requires-Dist: tokenizers
Project-URL: Bug Tracker, https://github.com/iscc/iscc-sct/issues
Project-URL: Changelog, https://github.com/iscc/iscc-sct/blob/main/CHANGELOG.md
Project-URL: Documentation, https://github.com/iscc/iscc-sct
Project-URL: Donate, https://iscc.foundation/support
Project-URL: Homepage, https://iscc.codes
Project-URL: Repository, https://github.com/iscc/iscc-sct
Project-URL: Twitter, https://twitter.com/iscc_foundation
